dover_lap/__init__.py
dover_lap/dover_lap.py
dover_lap/libs/__init__.py
dover_lap/libs/rttm.py
dover_lap/libs/turn.py
dover_lap/libs/uem.py
dover_lap/libs/utils.py
dover_lap/src/__init__.py
dover_lap/src/doverlap.py
dover_lap/src/label_mapping.py
dover_lap/src/label_voting.py
dover_lap/src/mapping/__init__.py
dover_lap/src/mapping/greedy.py
dover_lap/src/mapping/hungarian.py
dover_lap/src/mapping/map_utils.py
dover_lap/src/voting/__init__.py
dover_lap/src/voting/average.py
dover_lap-1.3.1.dist-info/LICENSE
dover_lap-1.3.1.dist-info/METADATA
dover_lap-1.3.1.dist-info/WHEEL
dover_lap-1.3.1.dist-info/entry_points.txt
dover_lap-1.3.1.dist-info/top_level.txt
dover_lap-1.3.1.dist-info/RECORD
