Metadata-Version: 2.1
Name: dover-lap
Version: 1.3.1
Summary: Combine overlap-aware diarization output RTTMs
Home-page: https://github.com/desh2608/dover-lap
Author: Desh Raj
Author-email: r.desh26@gmail.com
License: Apache-2.0 License
Keywords: diarization dover
Classifier: Development Status :: 3 - Alpha
Classifier: Topic :: Utilities
Classifier: License :: OSI Approved :: BSD License
License-File: LICENSE
Requires-Dist: intervaltree >=3.0.1
Requires-Dist: numpy >=1.18.1
Requires-Dist: click >=7.1.2
Requires-Dist: scipy >=1.5.4
Requires-Dist: spy-der >=0.4.0
